{"name":"Delete an active item","id":"deleting-todos;delete-an-active-item","testSteps":[{"number":1,"description":"Given that Jane has a todo list containing Buy some milk, Walk the dog","duration":1044,"startTime":"2022-03-17T20:19:30.071640870Z[Etc/UTC]","screenshots":[{"screenshot":"2a3f3a161f4738803ca024a42772879f6fe081b16753f44f69838741ff449c1b.png","timeStamp":1647548371115}],"result":"SUCCESS","precondition":false,"level":0,"children":[{"number":2,"description":"Jane starts with a todo list containing Buy some milk, Walk the dog","duration":1032,"startTime":"2022-03-17T20:19:30.080826691Z[Etc/UTC]","screenshots":[{"screenshot":"2a3f3a161f4738803ca024a42772879f6fe081b16753f44f69838741ff449c1b.png","timeStamp":1647548371113}],"result":"SUCCESS","precondition":false,"level":1,"children":[{"number":3,"description":"Jane opens the home.page page","duration":645,"startTime":"2022-03-17T20:19:30.082259210Z[Etc/UTC]","screenshots":[{"screenshot":"a385aec9d35a6fc7f4eb9c6069bbb0e4b3317c3d623e54fd3195ad5d99d9ebe7.png","timeStamp":1647548370727}],"result":"SUCCESS","precondition":false,"level":2},{"number":4,"description":"Jane adds the todo items called: [Buy some milk, Walk the dog]","duration":372,"startTime":"2022-03-17T20:19:30.730052861Z[Etc/UTC]","screenshots":[{"screenshot":"a385aec9d35a6fc7f4eb9c6069bbb0e4b3317c3d623e54fd3195ad5d99d9ebe7.png","timeStamp":1647548370732},{"screenshot":"2a3f3a161f4738803ca024a42772879f6fe081b16753f44f69838741ff449c1b.png","timeStamp":1647548371102}],"result":"SUCCESS","precondition":false,"level":2,"children":[{"number":5,"description":"Jane adds a todo item called: Buy some milk","duration":196,"startTime":"2022-03-17T20:19:30.736344144Z[Etc/UTC]","screenshots":[{"screenshot":"a385aec9d35a6fc7f4eb9c6069bbb0e4b3317c3d623e54fd3195ad5d99d9ebe7.png","timeStamp":1647548370740},{"screenshot":"f9dfd964e4a533376aa4e09fd3311e43b045bebd34f95106435b6fb76c028ecc.png","timeStamp":1647548370932}],"result":"SUCCESS","precondition":false,"level":3,"children":[{"number":6,"description":"Jane enters \u0027Buy some milk\u0027 then hits [RETURN] into \u0027What needs to be done?\u0027 field","duration":187,"startTime":"2022-03-17T20:19:30.741165908Z[Etc/UTC]","screenshots":[{"screenshot":"a385aec9d35a6fc7f4eb9c6069bbb0e4b3317c3d623e54fd3195ad5d99d9ebe7.png","timeStamp":1647548370746},{"screenshot":"f9dfd964e4a533376aa4e09fd3311e43b045bebd34f95106435b6fb76c028ecc.png","timeStamp":1647548370928}],"result":"SUCCESS","precondition":false,"level":4}]},{"number":7,"description":"Jane adds a todo item called: Walk the dog","duration":161,"startTime":"2022-03-17T20:19:30.937775978Z[Etc/UTC]","screenshots":[{"screenshot":"f9dfd964e4a533376aa4e09fd3311e43b045bebd34f95106435b6fb76c028ecc.png","timeStamp":1647548370941},{"screenshot":"2a3f3a161f4738803ca024a42772879f6fe081b16753f44f69838741ff449c1b.png","timeStamp":1647548371099}],"result":"SUCCESS","precondition":false,"level":3,"children":[{"number":8,"description":"Jane enters \u0027Walk the dog\u0027 then hits [RETURN] into \u0027What needs to be done?\u0027 field","duration":152,"startTime":"2022-03-17T20:19:30.942717143Z[Etc/UTC]","screenshots":[{"screenshot":"f9dfd964e4a533376aa4e09fd3311e43b045bebd34f95106435b6fb76c028ecc.png","timeStamp":1647548370947},{"screenshot":"2a3f3a161f4738803ca024a42772879f6fe081b16753f44f69838741ff449c1b.png","timeStamp":1647548371094}],"result":"SUCCESS","precondition":false,"level":4}]}]}]}]},{"number":9,"description":"When she deletes the task called \u0027Walk the dog\u0027","duration":117,"startTime":"2022-03-17T20:19:31.116488205Z[Etc/UTC]","screenshots":[{"screenshot":"f9dfd964e4a533376aa4e09fd3311e43b045bebd34f95106435b6fb76c028ecc.png","timeStamp":1647548371234}],"result":"SUCCESS","precondition":false,"level":0,"children":[{"number":10,"description":"she deletes the item Walk the dog","duration":105,"startTime":"2022-03-17T20:19:31.125907827Z[Etc/UTC]","screenshots":[{"screenshot":"f9dfd964e4a533376aa4e09fd3311e43b045bebd34f95106435b6fb76c028ecc.png","timeStamp":1647548371231}],"result":"SUCCESS","precondition":false,"level":1,"children":[{"number":11,"description":"she clicks on the delete item button","duration":100,"startTime":"2022-03-17T20:19:31.128816165Z[Etc/UTC]","screenshots":[{"screenshot":"f9dfd964e4a533376aa4e09fd3311e43b045bebd34f95106435b6fb76c028ecc.png","timeStamp":1647548371229}],"result":"SUCCESS","precondition":false,"level":2}]}]},{"number":12,"description":"Then her todo list should contain Buy some milk","duration":32,"startTime":"2022-03-17T20:19:31.234540741Z[Etc/UTC]","screenshots":[{"screenshot":"f9dfd964e4a533376aa4e09fd3311e43b045bebd34f95106435b6fb76c028ecc.png","timeStamp":1647548371267}],"result":"SUCCESS","precondition":false,"level":0,"children":[{"number":13,"description":"Then the items displayed should be ([Buy some milk])","duration":27,"startTime":"2022-03-17T20:19:31.236920972Z[Etc/UTC]","screenshots":[{"screenshot":"f9dfd964e4a533376aa4e09fd3311e43b045bebd34f95106435b6fb76c028ecc.png","timeStamp":1647548371264}],"result":"SUCCESS","precondition":false,"level":1}]}],"userStory":{"id":"deleting-todos","storyName":"Deleting todos","displayName":"Deleting todos","path":"maintain_my_todo_list/deleting_todos.feature","narrative":"  In order to make me feel **a sense of accomplishment**\n  As a tidy person\n  I want to be to delete the tasks once I am done with them","type":"feature"},"featureTag":{"name":"Maintain my todo list/Deleting todos","type":"feature","displayName":"Maintain my todo list/Deleting todos"},"title":"Delete an active item","description":"","tags":[{"name":"deleting","type":"tag","displayName":"deleting"},{"name":"Maintain my todo list/Deleting todos","type":"feature","displayName":"Deleting todos"},{"name":"cucumber","type":"tag","displayName":"cucumber"},{"name":"Maintain my todo list","type":"capability","displayName":"Maintain my todo list"}],"startTime":"2022-03-17T20:19:30.062621651Z[Etc/UTC]","duration":1205,"projectKey":"","sessionId":"315779c7460b37d458234099db4ca5f0","driver":"chrome:jane","isManualTestingUpToDate":false,"manual":false,"testSource":"Cucumber","actors":[{"name":"Jane","can":["browse the web"]}],"result":"SUCCESS"}